{
    "acquisition_software": "pychron py3/18.2",
    "aliquot": 304,
    "analysis_type": "air",
    "analyst_name": "lemorgan",
    "collection_version": "1.0:1.0",
    "comment": "",
    "commit": "b872127c834d0fa0e578bcf63cd4e61d66017bd4",
    "conditionals": null,
    "data_reduction_software": "pychron py3/18.2",
    "detectors": {
        "AX": {
            "deflection": 0.0,
            "gain": 1
        },
        "H1": {
            "deflection": 0.0,
            "gain": 1
        },
        "H2": {
            "deflection": 0.0,
            "gain": 1
        },
        "L1": {
            "deflection": 0.0,
            "gain": 1
        },
        "L2(CDD)": {
            "deflection": 0.0,
            "gain": 1
        }
    },
    "environmental": {
        "lab_humiditys": [],
        "lab_pneumatics": [],
        "lab_temperatures": []
    },
    "experiment_queue_name": "BABACut",
    "extraction": "helix_air.py",
    "identifier": "a-01-H",
    "increment": null,
    "instrument_name": "",
    "intensity_scalar": 0.0,
    "irradiation": "NoIrradiation",
    "irradiation_level": "A",
    "irradiation_position": 2,
    "isotopes": {
        "Ar36": {
            "detector": "L2(CDD)",
            "name": "Ar36",
            "serial_id": "00000"
        },
        "Ar37": {
            "detector": "L1",
            "name": "Ar37",
            "serial_id": "00000"
        },
        "Ar38": {
            "detector": "AX",
            "name": "Ar38",
            "serial_id": "00000"
        },
        "Ar39": {
            "detector": "H1",
            "name": "Ar39",
            "serial_id": "00000"
        },
        "Ar40": {
            "detector": "H2",
            "name": "Ar40",
            "serial_id": "00000"
        }
    },
    "laboratory": "",
    "mass_spectrometer": "Helix",
    "material": "Gas",
    "measurement": "helix_air.py",
    "post_equilibration": "helix_pump_prep.py",
    "post_measurement": "helix_pump_ms.py",
    "principal_investigator": "",
    "project": "REFERENCES",
    "queue_conditionals_name": "",
    "repository_identifier": "Helix_air181",
    "sample": "air",
    "source": {
        "emission": 599.129,
        "trap": 168.721
    },
    "spec_sha": "e83529eda11b38ec61c7322ca96114eec73095d1",
    "timestamp": "2018-07-10T14:08:40.228618",
    "tripped_conditional": null,
    "username": "lemorgan",
    "uuid": "6fa4f368-f73d-4170-8df6-b7e7638d2d75",
    "whiff_result": null
}