{
    "acquisition_software": "pychron py3/18.2",
    "aliquot": 313,
    "analysis_type": "air",
    "analyst_name": "lemorgan",
    "collection_version": "1.0:1.0",
    "comment": "",
    "commit": "2abe5974ea0e4b5bd11c0b2ae0ade36bd10d2828",
    "conditionals": null,
    "data_reduction_software": "pychron py3/18.2",
    "detectors": {
        "AX": {
            "deflection": 0.0,
            "gain": 1
        },
        "H1": {
            "deflection": 0.0,
            "gain": 1
        },
        "H2": {
            "deflection": 0.0,
            "gain": 1
        },
        "L1": {
            "deflection": 0.0,
            "gain": 1
        },
        "L2(CDD)": {
            "deflection": 0.0,
            "gain": 1
        }
    },
    "environmental": {
        "lab_humiditys": [],
        "lab_pneumatics": [],
        "lab_temperatures": []
    },
    "experiment_queue_name": "BABACut",
    "extraction": "helix_air.py",
    "identifier": "a-01-H",
    "increment": null,
    "instrument_name": "",
    "intensity_scalar": 0.0,
    "irradiation": "NoIrradiation",
    "irradiation_level": "A",
    "irradiation_position": 2,
    "isotopes": {
        "Ar36": {
            "detector": "L2(CDD)",
            "name": "Ar36",
            "serial_id": "00000"
        },
        "Ar37": {
            "detector": "L1",
            "name": "Ar37",
            "serial_id": "00000"
        },
        "Ar38": {
            "detector": "AX",
            "name": "Ar38",
            "serial_id": "00000"
        },
        "Ar39": {
            "detector": "H1",
            "name": "Ar39",
            "serial_id": "00000"
        },
        "Ar40": {
            "detector": "H2",
            "name": "Ar40",
            "serial_id": "00000"
        }
    },
    "laboratory": "",
    "mass_spectrometer": "Helix",
    "material": "Gas",
    "measurement": "helix_air.py",
    "post_equilibration": "helix_pump_prep.py",
    "post_measurement": "helix_pump_ms.py",
    "principal_investigator": "",
    "project": "REFERENCES",
    "queue_conditionals_name": "",
    "repository_identifier": "Helix_air181",
    "sample": "air",
    "source": {
        "emission": 598.642,
        "trap": 168.498
    },
    "spec_sha": "5af6e477ac342bd6887269860f395802f37d58ac",
    "timestamp": "2018-07-12T09:55:36.672673",
    "tripped_conditional": null,
    "username": "lemorgan",
    "uuid": "e80fdcdc-8207-41ec-bf4a-e24526bc2ba0",
    "whiff_result": null
}